MANIFEST.in
__init__.py
daemon.py
depot
depot.py
setup.py
python_depot.egg-info/PKG-INFO
python_depot.egg-info/SOURCES.txt
python_depot.egg-info/dependency_links.txt
python_depot.egg-info/top_level.txt